{
  "generatedAt": "2026-03-09T10:58:50.790Z",
  "source": "indiavotes",
  "parentSelection": {
    "state": "bihar",
    "stateLabel": "Bihar [2000 Onwards]",
    "stateVersionSlug": "bihar-2000-onwards",
    "geographyVersionId": "bihar-2000-onwards",
    "house": "VS",
    "year": 2025,
    "electionId": 303,
    "stateId": 58
  },
  "constituency": "Narpatganj",
  "constituencyNumber": 46,
  "district": "Araria",
  "reservationType": "GEN",
  "detailFileName": "bihar-2000-onwards-vs-2025-46-narpatganj-detail.json",
  "note": "Local constituency detail captured from IndiaVotes and staged inside Election Atlas so the atlas no longer needs an outbound click for this seat.",
  "parsed": {
    "winner": {
      "position": 1,
      "candidate": "Devanti Yadav",
      "votes": 120557,
      "voteShare": 49.9,
      "party": "Bharatiya Janta Party",
      "partyUrl": "https://www.indiavotes.com/party/ac_info/143/303/58"
    },
    "runnerUp": {
      "position": 2,
      "candidate": "Manish Yadav",
      "votes": 95204,
      "voteShare": 39.4,
      "party": "Rashtriya Janata Dal",
      "partyUrl": "https://www.indiavotes.com/party/ac_info/461/303/58"
    },
    "partyVoteTotals": [
      {
        "party": "Bharatiya Janta Party",
        "votes": 120557
      },
      {
        "party": "Rashtriya Janata Dal",
        "votes": 95204
      },
      {
        "party": "Independent",
        "votes": 18376
      },
      {
        "party": "Rashtriya Jansambhavna Party",
        "votes": 1696
      },
      {
        "party": "Jan Suraaj Party",
        "votes": 1688
      },
      {
        "party": "Bhartiya Lok Chetna Party",
        "votes": 290
      },
      {
        "party": "Rashtrawadi Janlok Party (Satya)",
        "votes": 281
      },
      {
        "party": "The National Road Map Party Of India",
        "votes": 278
      },
      {
        "party": "Prism",
        "votes": 244
      },
      {
        "party": "Apna Adhikar Party",
        "votes": 237
      }
    ],
    "candidateRows": [
      {
        "position": 1,
        "candidate": "Devanti Yadav",
        "votes": 120557,
        "voteShare": 49.9,
        "party": "Bharatiya Janta Party",
        "partyUrl": "https://www.indiavotes.com/party/ac_info/143/303/58"
      },
      {
        "position": 2,
        "candidate": "Manish Yadav",
        "votes": 95204,
        "voteShare": 39.4,
        "party": "Rashtriya Janata Dal",
        "partyUrl": "https://www.indiavotes.com/party/ac_info/461/303/58"
      },
      {
        "position": 3,
        "candidate": "Anil Kumar Yadav",
        "votes": 10669,
        "voteShare": 4.4,
        "party": "Independent",
        "partyUrl": "https://www.indiavotes.com/party/ac_info/7/303/58"
      },
      {
        "position": 4,
        "candidate": "Shravan Kumar Das",
        "votes": 3761,
        "voteShare": 1.6,
        "party": "Independent",
        "partyUrl": "https://www.indiavotes.com/party/ac_info/7/303/58"
      },
      {
        "position": 6,
        "candidate": "Aanant Kumar Roy",
        "votes": 1696,
        "voteShare": 0.7,
        "party": "Rashtriya Jansambhavna Party",
        "partyUrl": "https://www.indiavotes.com/party/ac_info/2080/303/58"
      },
      {
        "position": 7,
        "candidate": "Janardan Yadav",
        "votes": 1688,
        "voteShare": 0.7,
        "party": "Jan Suraaj Party",
        "partyUrl": "https://www.indiavotes.com/party/ac_info/3121/303/58"
      },
      {
        "position": 8,
        "candidate": "Akhilesh Kumar",
        "votes": 1196,
        "voteShare": 0.5,
        "party": "Independent",
        "partyUrl": "https://www.indiavotes.com/party/ac_info/7/303/58"
      },
      {
        "position": 9,
        "candidate": "Bechan Ram",
        "votes": 1170,
        "voteShare": 0.5,
        "party": "Independent",
        "partyUrl": "https://www.indiavotes.com/party/ac_info/7/303/58"
      },
      {
        "position": 10,
        "candidate": "Jitendra Yadav",
        "votes": 950,
        "voteShare": 0.4,
        "party": "Independent",
        "partyUrl": "https://www.indiavotes.com/party/ac_info/7/303/58"
      },
      {
        "position": 11,
        "candidate": "Alok Kumar",
        "votes": 630,
        "voteShare": 0.3,
        "party": "Independent",
        "partyUrl": "https://www.indiavotes.com/party/ac_info/7/303/58"
      },
      {
        "position": 12,
        "candidate": "Chandresh Kumar",
        "votes": 290,
        "voteShare": 0.1,
        "party": "Bhartiya Lok Chetna Party",
        "partyUrl": "https://www.indiavotes.com/party/ac_info/2513/303/58"
      },
      {
        "position": 13,
        "candidate": "Pappu Kumar Singh",
        "votes": 281,
        "voteShare": 0.1,
        "party": "Rashtrawadi Janlok Party (Satya)",
        "partyUrl": "https://www.indiavotes.com/party/ac_info/2537/303/58"
      },
      {
        "position": 14,
        "candidate": "Shoab Alam",
        "votes": 278,
        "voteShare": 0.1,
        "party": "The National Road Map Party Of India",
        "partyUrl": "https://www.indiavotes.com/party/ac_info/1793/303/58"
      },
      {
        "position": 15,
        "candidate": "Lalit Kumar Sah",
        "votes": 244,
        "voteShare": 0.1,
        "party": "Prism",
        "partyUrl": "https://www.indiavotes.com/party/ac_info/504/303/58"
      },
      {
        "position": 16,
        "candidate": "Mohammad Aslam Beg",
        "votes": 237,
        "voteShare": 0.1,
        "party": "Apna Adhikar Party",
        "partyUrl": "https://www.indiavotes.com/party/ac_info/2505/303/58"
      }
    ]
  }
}
