{
  "generatedAt": "2026-03-09T10:59:05.548Z",
  "source": "indiavotes",
  "parentSelection": {
    "state": "chhattisgarh",
    "stateLabel": "Chhattisgarh",
    "stateVersionSlug": "chhattisgarh",
    "geographyVersionId": "chhattisgarh-default",
    "house": "VS",
    "year": 2023,
    "electionId": 293,
    "stateId": 54
  },
  "constituency": "Chitrakot",
  "constituencyNumber": 87,
  "district": "Bastar",
  "reservationType": "ST",
  "detailFileName": "chhattisgarh-vs-2023-87-chitrakot-detail.json",
  "note": "Local constituency detail captured from IndiaVotes and staged inside Election Atlas so the atlas no longer needs an outbound click for this seat.",
  "parsed": {
    "winner": {
      "position": 1,
      "candidate": "Vinayak Goyal",
      "votes": 63954,
      "voteShare": 43.7,
      "party": "Bharatiya Janta Party",
      "partyUrl": "https://www.indiavotes.com/party/ac_info/143/293/54"
    },
    "runnerUp": {
      "position": 2,
      "candidate": "Deepak Kumar Baij",
      "votes": 55584,
      "voteShare": 38,
      "party": "Indian National Congress",
      "partyUrl": "https://www.indiavotes.com/party/ac_info/1/293/54"
    },
    "partyVoteTotals": [
      {
        "party": "Bharatiya Janta Party",
        "votes": 63954
      },
      {
        "party": "Indian National Congress",
        "votes": 55584
      },
      {
        "party": "Communist Party Of India",
        "votes": 5051
      },
      {
        "party": "Aam Aadmi Party",
        "votes": 4644
      },
      {
        "party": "Janta Congress Chhattisgarh (J)",
        "votes": 4184
      },
      {
        "party": "Bahujan Samaj Party",
        "votes": 3493
      },
      {
        "party": "Sarv Adi Dal",
        "votes": 2028
      }
    ],
    "candidateRows": [
      {
        "position": 1,
        "candidate": "Vinayak Goyal",
        "votes": 63954,
        "voteShare": 43.7,
        "party": "Bharatiya Janta Party",
        "partyUrl": "https://www.indiavotes.com/party/ac_info/143/293/54"
      },
      {
        "position": 2,
        "candidate": "Deepak Kumar Baij",
        "votes": 55584,
        "voteShare": 38,
        "party": "Indian National Congress",
        "partyUrl": "https://www.indiavotes.com/party/ac_info/1/293/54"
      },
      {
        "position": 3,
        "candidate": "Ramu Ram Mourya",
        "votes": 5051,
        "voteShare": 3.5,
        "party": "Communist Party Of India",
        "partyUrl": "https://www.indiavotes.com/party/ac_info/14/293/54"
      },
      {
        "position": 4,
        "candidate": "Bomdha Mandavi",
        "votes": 4644,
        "voteShare": 3.2,
        "party": "Aam Aadmi Party",
        "partyUrl": "https://www.indiavotes.com/party/ac_info/1504/293/54"
      },
      {
        "position": 5,
        "candidate": "Bharat Kashyap",
        "votes": 4184,
        "voteShare": 2.9,
        "party": "Janta Congress Chhattisgarh (J)",
        "partyUrl": "https://www.indiavotes.com/party/ac_info/2091/293/54"
      },
      {
        "position": 6,
        "candidate": "Sannu Poyam",
        "votes": 3493,
        "voteShare": 2.4,
        "party": "Bahujan Samaj Party",
        "partyUrl": "https://www.indiavotes.com/party/ac_info/1381/293/54"
      },
      {
        "position": 7,
        "candidate": "Ramlal Podiyam",
        "votes": 2028,
        "voteShare": 1.4,
        "party": "Sarv Adi Dal",
        "partyUrl": "https://www.indiavotes.com/party/ac_info/2774/293/54"
      }
    ]
  }
}
