{
  "generatedAt": "2026-03-09T14:58:45.256Z",
  "source": "indiavotes",
  "parentSelection": {
    "state": "jammu-and-kashmir",
    "stateLabel": "Jammu & Kashmir",
    "stateVersionSlug": "jammu-kashmir",
    "geographyVersionId": "jammu-and-kashmir-default",
    "house": "VS",
    "year": 2014,
    "electionId": 242,
    "stateId": 32
  },
  "constituency": "Pulwama",
  "constituencyNumber": 33,
  "district": "Pulwama",
  "reservationType": "GEN",
  "detailFileName": "jammu-kashmir-vs-2014-33-pulwama-detail.json",
  "note": "Local constituency detail captured from IndiaVotes and staged inside Election Atlas so the atlas no longer needs an outbound click for this seat.",
  "parsed": {
    "winner": {
      "position": 1,
      "candidate": "Mohd. Khalil Band",
      "votes": 11631,
      "voteShare": 38.6,
      "party": "Jammu & Kashmir Peoples Democratic Party",
      "partyUrl": "https://www.indiavotes.com/party/ac_info/596/242/32"
    },
    "runnerUp": {
      "position": 2,
      "candidate": "Ghulam Nabi Wani",
      "votes": 10599,
      "voteShare": 35.1,
      "party": "Jammu & Kashmir National Conference",
      "partyUrl": "https://www.indiavotes.com/party/ac_info/78/242/32"
    },
    "partyVoteTotals": [
      {
        "party": "Jammu & Kashmir Peoples Democratic Party",
        "votes": 11631
      },
      {
        "party": "Jammu & Kashmir National Conference",
        "votes": 10599
      },
      {
        "party": "Independent",
        "votes": 2908
      },
      {
        "party": "Jammu And Kashmir People Democratic Front (Secular)",
        "votes": 1850
      },
      {
        "party": "Indian National Congress",
        "votes": 1558
      },
      {
        "party": "Bharatiya Janta Party",
        "votes": 672
      },
      {
        "party": "Jammu & Kashmir People Conference",
        "votes": 661
      }
    ],
    "candidateRows": [
      {
        "position": 1,
        "candidate": "Mohd. Khalil Band",
        "votes": 11631,
        "voteShare": 38.6,
        "party": "Jammu & Kashmir Peoples Democratic Party",
        "partyUrl": "https://www.indiavotes.com/party/ac_info/596/242/32"
      },
      {
        "position": 2,
        "candidate": "Ghulam Nabi Wani",
        "votes": 10599,
        "voteShare": 35.1,
        "party": "Jammu & Kashmir National Conference",
        "partyUrl": "https://www.indiavotes.com/party/ac_info/78/242/32"
      },
      {
        "position": 3,
        "candidate": "Ab. Quyoom Mir",
        "votes": 1850,
        "voteShare": 6.1,
        "party": "Jammu And Kashmir People Democratic Front (Secular)",
        "partyUrl": "https://www.indiavotes.com/party/ac_info/1753/242/32"
      },
      {
        "position": 4,
        "candidate": "Sana Ullah Dar",
        "votes": 1760,
        "voteShare": 5.8,
        "party": "Independent",
        "partyUrl": "https://www.indiavotes.com/party/ac_info/7/242/32"
      },
      {
        "position": 5,
        "candidate": "Bashir Ahmad Magrey",
        "votes": 1558,
        "voteShare": 5.2,
        "party": "Indian National Congress",
        "partyUrl": "https://www.indiavotes.com/party/ac_info/1/242/32"
      },
      {
        "position": 6,
        "candidate": "Riyaz Ahmad Mir",
        "votes": 672,
        "voteShare": 2.2,
        "party": "Bharatiya Janta Party",
        "partyUrl": "https://www.indiavotes.com/party/ac_info/143/242/32"
      },
      {
        "position": 7,
        "candidate": "Bashir Ahmad Malik",
        "votes": 669,
        "voteShare": 2.2,
        "party": "Independent",
        "partyUrl": "https://www.indiavotes.com/party/ac_info/7/242/32"
      },
      {
        "position": 8,
        "candidate": "Farooq Ahmad Mir",
        "votes": 661,
        "voteShare": 2.2,
        "party": "Jammu & Kashmir People Conference",
        "partyUrl": "https://www.indiavotes.com/party/ac_info/773/242/32"
      },
      {
        "position": 9,
        "candidate": "Masuod Hussain Wani",
        "votes": 260,
        "voteShare": 0.9,
        "party": "Independent",
        "partyUrl": "https://www.indiavotes.com/party/ac_info/7/242/32"
      },
      {
        "position": 10,
        "candidate": "Abdul Gani Shah",
        "votes": 219,
        "voteShare": 0.7,
        "party": "Independent",
        "partyUrl": "https://www.indiavotes.com/party/ac_info/7/242/32"
      }
    ]
  }
}
