{
  "generatedAt": "2026-03-09T11:02:32.901Z",
  "source": "indiavotes",
  "parentSelection": {
    "state": "maharashtra",
    "stateLabel": "Maharashtra",
    "stateVersionSlug": "maharashtra",
    "geographyVersionId": "maharashtra-default",
    "house": "VS",
    "year": 2024,
    "electionId": 300,
    "stateId": 30
  },
  "constituency": "Ramtek",
  "constituencyNumber": 59,
  "district": "Nagpur",
  "reservationType": "GEN",
  "detailFileName": "maharashtra-vs-2024-59-ramtek-detail.json",
  "note": "Local constituency detail captured from IndiaVotes and staged inside Election Atlas so the atlas no longer needs an outbound click for this seat.",
  "parsed": {
    "winner": {
      "position": 1,
      "candidate": "Ashish Nandkishore Jaiswal(VAKIL)",
      "votes": 107967,
      "voteShare": 52,
      "party": "Shiv Sena",
      "partyUrl": "https://www.indiavotes.com/party/ac_info/110/300/30"
    },
    "runnerUp": {
      "position": 2,
      "candidate": "Rajendra Bhaurao Mulak",
      "votes": 81412,
      "voteShare": 39.2,
      "party": "Independent",
      "partyUrl": "https://www.indiavotes.com/party/ac_info/7/300/30"
    },
    "partyVoteTotals": [
      {
        "party": "Shiv Sena",
        "votes": 107967
      },
      {
        "party": "Independent",
        "votes": 90096
      },
      {
        "party": "Shiv Sena (Uddhav Balasaheb Thackrey)",
        "votes": 5501
      },
      {
        "party": "Bahujan Samaj Party",
        "votes": 2567
      },
      {
        "party": "Bahujan Republican Socialist Party",
        "votes": 224
      },
      {
        "party": "All India Forward Bloc",
        "votes": 194
      },
      {
        "party": "Rashtriya Gondvana Party",
        "votes": 189
      },
      {
        "party": "Hindustan Janta Party",
        "votes": 92
      },
      {
        "party": "Bhim Sena",
        "votes": 66
      }
    ],
    "candidateRows": [
      {
        "position": 1,
        "candidate": "Ashish Nandkishore Jaiswal(VAKIL)",
        "votes": 107967,
        "voteShare": 52,
        "party": "Shiv Sena",
        "partyUrl": "https://www.indiavotes.com/party/ac_info/110/300/30"
      },
      {
        "position": 2,
        "candidate": "Rajendra Bhaurao Mulak",
        "votes": 81412,
        "voteShare": 39.2,
        "party": "Independent",
        "partyUrl": "https://www.indiavotes.com/party/ac_info/7/300/30"
      },
      {
        "position": 3,
        "candidate": "Vishal Gangadharrao Barbate",
        "votes": 5501,
        "voteShare": 2.7,
        "party": "Shiv Sena (Uddhav Balasaheb Thackrey)",
        "partyUrl": "https://www.indiavotes.com/party/ac_info/2921/300/30"
      },
      {
        "position": 4,
        "candidate": "Chandrapal Nathusao Choukasey",
        "votes": 3254,
        "voteShare": 1.6,
        "party": "Independent",
        "partyUrl": "https://www.indiavotes.com/party/ac_info/7/300/30"
      },
      {
        "position": 5,
        "candidate": "Chandrashekhar Namade Bhimte",
        "votes": 2567,
        "voteShare": 1.2,
        "party": "Bahujan Samaj Party",
        "partyUrl": "https://www.indiavotes.com/party/ac_info/1381/300/30"
      },
      {
        "position": 6,
        "candidate": "Vijay Natthuji Hatwar",
        "votes": 1592,
        "voteShare": 0.8,
        "party": "Independent",
        "partyUrl": "https://www.indiavotes.com/party/ac_info/7/300/30"
      },
      {
        "position": 7,
        "candidate": "Sachin Marotrao Kirpan",
        "votes": 1544,
        "voteShare": 0.7,
        "party": "Independent",
        "partyUrl": "https://www.indiavotes.com/party/ac_info/7/300/30"
      },
      {
        "position": 8,
        "candidate": "Manoj Kothuji Bawane",
        "votes": 823,
        "voteShare": 0.4,
        "party": "Independent",
        "partyUrl": "https://www.indiavotes.com/party/ac_info/7/300/30"
      },
      {
        "position": 9,
        "candidate": "Ambade Prafulla Premdas",
        "votes": 744,
        "voteShare": 0.4,
        "party": "Independent",
        "partyUrl": "https://www.indiavotes.com/party/ac_info/7/300/30"
      },
      {
        "position": 11,
        "candidate": "Roshan Rupchand Gade",
        "votes": 278,
        "voteShare": 0.1,
        "party": "Independent",
        "partyUrl": "https://www.indiavotes.com/party/ac_info/7/300/30"
      },
      {
        "position": 12,
        "candidate": "Rameshwar Mangalji Inwate",
        "votes": 273,
        "voteShare": 0.1,
        "party": "Independent",
        "partyUrl": "https://www.indiavotes.com/party/ac_info/7/300/30"
      },
      {
        "position": 13,
        "candidate": "Vishesh Vasanta Futane",
        "votes": 224,
        "voteShare": 0.1,
        "party": "Bahujan Republican Socialist Party",
        "partyUrl": "https://www.indiavotes.com/party/ac_info/2387/300/30"
      },
      {
        "position": 14,
        "candidate": "Adv. Dr. Gowardhan Namdeo Somdeve",
        "votes": 194,
        "voteShare": 0.1,
        "party": "All India Forward Bloc",
        "partyUrl": "https://www.indiavotes.com/party/ac_info/1364/300/30"
      },
      {
        "position": 15,
        "candidate": "Bawankule Rajendra Bhimrao Shahir",
        "votes": 189,
        "voteShare": 0.1,
        "party": "Rashtriya Gondvana Party",
        "partyUrl": "https://www.indiavotes.com/party/ac_info/840/300/30"
      },
      {
        "position": 16,
        "candidate": "Pukraj Krushnaji Kamde",
        "votes": 176,
        "voteShare": 0.1,
        "party": "Independent",
        "partyUrl": "https://www.indiavotes.com/party/ac_info/7/300/30"
      },
      {
        "position": 17,
        "candidate": "Pankaj Sevakram Masurkar",
        "votes": 92,
        "voteShare": 0,
        "party": "Hindustan Janta Party",
        "partyUrl": "https://www.indiavotes.com/party/ac_info/2261/300/30"
      },
      {
        "position": 18,
        "candidate": "Pradip Narayan Salve",
        "votes": 66,
        "voteShare": 0,
        "party": "Bhim Sena",
        "partyUrl": "https://www.indiavotes.com/party/ac_info/2922/300/30"
      }
    ]
  }
}
