{
  "generatedAt": "2026-03-09T11:02:45.388Z",
  "source": "indiavotes",
  "parentSelection": {
    "state": "manipur",
    "stateLabel": "Manipur",
    "stateVersionSlug": "manipur",
    "geographyVersionId": "manipur-default",
    "house": "VS",
    "year": 2022,
    "electionId": 288,
    "stateId": 24
  },
  "constituency": "Uripok",
  "constituencyNumber": 10,
  "district": "Imphal West",
  "reservationType": "GEN",
  "detailFileName": "manipur-vs-2022-10-uripok-detail.json",
  "note": "Local constituency detail captured from IndiaVotes and staged inside Election Atlas so the atlas no longer needs an outbound click for this seat.",
  "parsed": {
    "winner": {
      "position": 1,
      "candidate": "Khwairakpam Raghumani Singh",
      "votes": 8335,
      "voteShare": 36.6,
      "party": "Bharatiya Janta Party",
      "partyUrl": "https://www.indiavotes.com/party/ac_info/143/288/24"
    },
    "runnerUp": {
      "position": 2,
      "candidate": "Yumnam Joykumar Singh",
      "votes": 7426,
      "voteShare": 32.6,
      "party": "National People's Party",
      "partyUrl": "https://www.indiavotes.com/party/ac_info/1478/288/24"
    },
    "partyVoteTotals": [
      {
        "party": "Bharatiya Janta Party",
        "votes": 8335
      },
      {
        "party": "National People's Party",
        "votes": 7426
      },
      {
        "party": "Janata Dal (United)",
        "votes": 5472
      },
      {
        "party": "Indian National Congress",
        "votes": 1540
      }
    ],
    "candidateRows": [
      {
        "position": 1,
        "candidate": "Khwairakpam Raghumani Singh",
        "votes": 8335,
        "voteShare": 36.6,
        "party": "Bharatiya Janta Party",
        "partyUrl": "https://www.indiavotes.com/party/ac_info/143/288/24"
      },
      {
        "position": 2,
        "candidate": "Yumnam Joykumar Singh",
        "votes": 7426,
        "voteShare": 32.6,
        "party": "National People's Party",
        "partyUrl": "https://www.indiavotes.com/party/ac_info/1478/288/24"
      },
      {
        "position": 3,
        "candidate": "Khombongmayum Suresh Singh",
        "votes": 5472,
        "voteShare": 24,
        "party": "Janata Dal (United)",
        "partyUrl": "https://www.indiavotes.com/party/ac_info/536/288/24"
      },
      {
        "position": 4,
        "candidate": "Nunglepam Mahananda Singh",
        "votes": 1540,
        "voteShare": 6.8,
        "party": "Indian National Congress",
        "partyUrl": "https://www.indiavotes.com/party/ac_info/1/288/24"
      }
    ]
  }
}
