{
  "generatedAt": "2026-03-09T11:03:40.139Z",
  "source": "indiavotes",
  "parentSelection": {
    "state": "punjab",
    "stateLabel": "Punjab",
    "stateVersionSlug": "punjab",
    "geographyVersionId": "punjab-default",
    "house": "VS",
    "year": 2022,
    "electionId": 286,
    "stateId": 7
  },
  "constituency": "Dirba",
  "constituencyNumber": 100,
  "district": "Sangrur",
  "reservationType": "SC",
  "detailFileName": "punjab-vs-2022-100-dirba-detail.json",
  "note": "Local constituency detail captured from IndiaVotes and staged inside Election Atlas so the atlas no longer needs an outbound click for this seat.",
  "parsed": {
    "winner": {
      "position": 1,
      "candidate": "Harpal Singh Cheema",
      "votes": 82630,
      "voteShare": 57.3,
      "party": "Aam Aadmi Party",
      "partyUrl": "https://www.indiavotes.com/party/ac_info/1504/286/7"
    },
    "runnerUp": {
      "position": 2,
      "candidate": "Gulzar Singh Moonak",
      "votes": 31975,
      "voteShare": 22.2,
      "party": "Shiromani Akali Dal",
      "partyUrl": "https://www.indiavotes.com/party/ac_info/33/286/7"
    },
    "partyVoteTotals": [
      {
        "party": "Aam Aadmi Party",
        "votes": 82630
      },
      {
        "party": "Shiromani Akali Dal",
        "votes": 31975
      },
      {
        "party": "Indian National Congress",
        "votes": 10472
      },
      {
        "party": "Shiromani Akali Dal (Amritsar)(Simranjit Singh Mann)",
        "votes": 9000
      },
      {
        "party": "Shiromani Akali Dal (Sanyukt)",
        "votes": 4760
      },
      {
        "party": "Independent",
        "votes": 2860
      },
      {
        "party": "Sanyukt Sangharsh Party",
        "votes": 1194
      },
      {
        "party": "Communist Party Of India (MARXIST-LENINIST) (LIBERATION)",
        "votes": 723
      },
      {
        "party": "Jai Jawan Jai Kisan Party",
        "votes": 393
      },
      {
        "party": "Lok Insaaf Party",
        "votes": 248
      }
    ],
    "candidateRows": [
      {
        "position": 1,
        "candidate": "Harpal Singh Cheema",
        "votes": 82630,
        "voteShare": 57.3,
        "party": "Aam Aadmi Party",
        "partyUrl": "https://www.indiavotes.com/party/ac_info/1504/286/7"
      },
      {
        "position": 2,
        "candidate": "Gulzar Singh Moonak",
        "votes": 31975,
        "voteShare": 22.2,
        "party": "Shiromani Akali Dal",
        "partyUrl": "https://www.indiavotes.com/party/ac_info/33/286/7"
      },
      {
        "position": 3,
        "candidate": "Ajaib Singh Ratolan",
        "votes": 10472,
        "voteShare": 7.3,
        "party": "Indian National Congress",
        "partyUrl": "https://www.indiavotes.com/party/ac_info/1/286/7"
      },
      {
        "position": 4,
        "candidate": "Mandeep Singh",
        "votes": 9000,
        "voteShare": 6.2,
        "party": "Shiromani Akali Dal (Amritsar)(Simranjit Singh Mann)",
        "partyUrl": "https://www.indiavotes.com/party/ac_info/2184/286/7"
      },
      {
        "position": 5,
        "candidate": "Soma Singh",
        "votes": 4760,
        "voteShare": 3.3,
        "party": "Shiromani Akali Dal (Sanyukt)",
        "partyUrl": "https://www.indiavotes.com/party/ac_info/2624/286/7"
      },
      {
        "position": 6,
        "candidate": "Malvinder Singh",
        "votes": 1194,
        "voteShare": 0.8,
        "party": "Sanyukt Sangharsh Party",
        "partyUrl": "https://www.indiavotes.com/party/ac_info/2622/286/7"
      },
      {
        "position": 7,
        "candidate": "Lal Singh",
        "votes": 890,
        "voteShare": 0.6,
        "party": "Independent",
        "partyUrl": "https://www.indiavotes.com/party/ac_info/7/286/7"
      },
      {
        "position": 8,
        "candidate": "Avtar Singh Namberdar",
        "votes": 775,
        "voteShare": 0.5,
        "party": "Independent",
        "partyUrl": "https://www.indiavotes.com/party/ac_info/7/286/7"
      },
      {
        "position": 9,
        "candidate": "Gobind Singh Chhajli",
        "votes": 723,
        "voteShare": 0.5,
        "party": "Communist Party Of India (MARXIST-LENINIST) (LIBERATION)",
        "partyUrl": "https://www.indiavotes.com/party/ac_info/308/286/7"
      },
      {
        "position": 10,
        "candidate": "Ran Singh Mehlan",
        "votes": 723,
        "voteShare": 0.5,
        "party": "Independent",
        "partyUrl": "https://www.indiavotes.com/party/ac_info/7/286/7"
      },
      {
        "position": 11,
        "candidate": "Gurmeet Singh",
        "votes": 472,
        "voteShare": 0.3,
        "party": "Independent",
        "partyUrl": "https://www.indiavotes.com/party/ac_info/7/286/7"
      },
      {
        "position": 12,
        "candidate": "Amanpreet Singh",
        "votes": 393,
        "voteShare": 0.3,
        "party": "Jai Jawan Jai Kisan Party",
        "partyUrl": "https://www.indiavotes.com/party/ac_info/1889/286/7"
      },
      {
        "position": 13,
        "candidate": "Bikar Singh",
        "votes": 248,
        "voteShare": 0.2,
        "party": "Lok Insaaf Party",
        "partyUrl": "https://www.indiavotes.com/party/ac_info/1878/286/7"
      }
    ]
  }
}
