{
  "generatedAt": "2026-03-09T11:06:12.281Z",
  "source": "indiavotes",
  "parentSelection": {
    "state": "uttar-pradesh",
    "stateLabel": "Uttar Pradesh [2000 Onwards]",
    "stateVersionSlug": "uttar-pradesh-2000-onwards",
    "geographyVersionId": "uttar-pradesh-2000-onwards",
    "house": "VS",
    "year": 2022,
    "electionId": 289,
    "stateId": 60
  },
  "constituency": "Sahaswan",
  "constituencyNumber": 113,
  "district": "Budaun",
  "reservationType": "GEN",
  "detailFileName": "uttar-pradesh-2000-onwards-vs-2022-113-sahaswan-detail.json",
  "note": "Local constituency detail captured from IndiaVotes and staged inside Election Atlas so the atlas no longer needs an outbound click for this seat.",
  "parsed": {
    "winner": {
      "position": 1,
      "candidate": "Brajesh Yadav",
      "votes": 83673,
      "voteShare": 33.6,
      "party": "Samajwadi Party",
      "partyUrl": "https://www.indiavotes.com/party/ac_info/1341/289/60"
    },
    "runnerUp": {
      "position": 2,
      "candidate": "Musarrat Ali",
      "votes": 69728,
      "voteShare": 28,
      "party": "Bahujan Samaj Party",
      "partyUrl": "https://www.indiavotes.com/party/ac_info/1381/289/60"
    },
    "partyVoteTotals": [
      {
        "party": "Samajwadi Party",
        "votes": 83673
      },
      {
        "party": "Bahujan Samaj Party",
        "votes": 69728
      },
      {
        "party": "Bharatiya Janta Party",
        "votes": 66616
      },
      {
        "party": "Rashtriya Parivartan Dal",
        "votes": 24060
      },
      {
        "party": "Independent",
        "votes": 2759
      },
      {
        "party": "Indian National Congress",
        "votes": 1126
      },
      {
        "party": "Jan Seva Sahayak Party",
        "votes": 573
      },
      {
        "party": "Aam Aadmi Party",
        "votes": 438
      }
    ],
    "candidateRows": [
      {
        "position": 1,
        "candidate": "Brajesh Yadav",
        "votes": 83673,
        "voteShare": 33.6,
        "party": "Samajwadi Party",
        "partyUrl": "https://www.indiavotes.com/party/ac_info/1341/289/60"
      },
      {
        "position": 2,
        "candidate": "Musarrat Ali",
        "votes": 69728,
        "voteShare": 28,
        "party": "Bahujan Samaj Party",
        "partyUrl": "https://www.indiavotes.com/party/ac_info/1381/289/60"
      },
      {
        "position": 3,
        "candidate": "Dhirendra Kumar Bhardwaj",
        "votes": 66616,
        "voteShare": 26.8,
        "party": "Bharatiya Janta Party",
        "partyUrl": "https://www.indiavotes.com/party/ac_info/143/289/60"
      },
      {
        "position": 4,
        "candidate": "Kunal Singh",
        "votes": 24060,
        "voteShare": 9.7,
        "party": "Rashtriya Parivartan Dal",
        "partyUrl": "https://www.indiavotes.com/party/ac_info/644/289/60"
      },
      {
        "position": 5,
        "candidate": "Rajveer Singh",
        "votes": 1126,
        "voteShare": 0.5,
        "party": "Indian National Congress",
        "partyUrl": "https://www.indiavotes.com/party/ac_info/1/289/60"
      },
      {
        "position": 6,
        "candidate": "Ravendra Sarma",
        "votes": 969,
        "voteShare": 0.4,
        "party": "Independent",
        "partyUrl": "https://www.indiavotes.com/party/ac_info/7/289/60"
      },
      {
        "position": 7,
        "candidate": "Pravesh Kumar",
        "votes": 914,
        "voteShare": 0.4,
        "party": "Independent",
        "partyUrl": "https://www.indiavotes.com/party/ac_info/7/289/60"
      },
      {
        "position": 8,
        "candidate": "Rakesh Kumar Sharma",
        "votes": 876,
        "voteShare": 0.4,
        "party": "Independent",
        "partyUrl": "https://www.indiavotes.com/party/ac_info/7/289/60"
      },
      {
        "position": 9,
        "candidate": "Navab",
        "votes": 573,
        "voteShare": 0.2,
        "party": "Jan Seva Sahayak Party",
        "partyUrl": "https://www.indiavotes.com/party/ac_info/1968/289/60"
      },
      {
        "position": 10,
        "candidate": "Anil Kumar",
        "votes": 438,
        "voteShare": 0.2,
        "party": "Aam Aadmi Party",
        "partyUrl": "https://www.indiavotes.com/party/ac_info/1504/289/60"
      }
    ]
  }
}
