{
  "generatedAt": "2026-03-09T15:35:01.157Z",
  "source": "indiavotes",
  "parentSelection": {
    "state": "uttar-pradesh",
    "stateLabel": "Uttar Pradesh [2000 Onwards]",
    "stateVersionSlug": "uttar-pradesh-2000-onwards",
    "geographyVersionId": "uttar-pradesh-2000-onwards",
    "house": "VS",
    "year": 2012,
    "electionId": 220,
    "stateId": 60
  },
  "constituency": "Varanasi South",
  "constituencyNumber": 389,
  "district": "Varanasi",
  "reservationType": "GEN",
  "detailFileName": "uttar-pradesh-2000-onwards-vs-2012-389-varanasi-south-detail.json",
  "note": "Local constituency detail captured from IndiaVotes and staged inside Election Atlas so the atlas no longer needs an outbound click for this seat.",
  "parsed": {
    "winner": {
      "position": 1,
      "candidate": "Shyamdev Roy Chaudhari (Dada)",
      "votes": 57868,
      "voteShare": 38.2,
      "party": "Bharatiya Janta Party",
      "partyUrl": "https://www.indiavotes.com/party/ac_info/143/220/60"
    },
    "runnerUp": {
      "position": 2,
      "candidate": "Dr. Dayashankar Mishra #dayalu#",
      "votes": 44046,
      "voteShare": 29.1,
      "party": "Indian National Congress",
      "partyUrl": "https://www.indiavotes.com/party/ac_info/1/220/60"
    },
    "partyVoteTotals": [
      {
        "party": "Bharatiya Janta Party",
        "votes": 57868
      },
      {
        "party": "Indian National Congress",
        "votes": 44046
      },
      {
        "party": "Quami Ekta Dal",
        "votes": 20454
      },
      {
        "party": "Samajwadi Party",
        "votes": 14642
      },
      {
        "party": "Bahujan Samaj Party",
        "votes": 8841
      },
      {
        "party": "Independent",
        "votes": 1758
      },
      {
        "party": "Rashtriya Lokmanch",
        "votes": 1263
      },
      {
        "party": "Communist Party Of India",
        "votes": 993
      },
      {
        "party": "Rashtriya Ulama Council",
        "votes": 727
      },
      {
        "party": "Manavadhikar Janshakti Party",
        "votes": 437
      },
      {
        "party": "Pragtisheel Manav Samaj Party",
        "votes": 371
      }
    ],
    "candidateRows": [
      {
        "position": 1,
        "candidate": "Shyamdev Roy Chaudhari (Dada)",
        "votes": 57868,
        "voteShare": 38.2,
        "party": "Bharatiya Janta Party",
        "partyUrl": "https://www.indiavotes.com/party/ac_info/143/220/60"
      },
      {
        "position": 2,
        "candidate": "Dr. Dayashankar Mishra #dayalu#",
        "votes": 44046,
        "voteShare": 29.1,
        "party": "Indian National Congress",
        "partyUrl": "https://www.indiavotes.com/party/ac_info/1/220/60"
      },
      {
        "position": 3,
        "candidate": "Atahar Jamal Lari",
        "votes": 20454,
        "voteShare": 13.5,
        "party": "Quami Ekta Dal",
        "partyUrl": "https://www.indiavotes.com/party/ac_info/1262/220/60"
      },
      {
        "position": 4,
        "candidate": "Md. Istaqbal #babu#",
        "votes": 14642,
        "voteShare": 9.7,
        "party": "Samajwadi Party",
        "partyUrl": "https://www.indiavotes.com/party/ac_info/1341/220/60"
      },
      {
        "position": 5,
        "candidate": "Kaisar Ameen Ansari",
        "votes": 8841,
        "voteShare": 5.8,
        "party": "Bahujan Samaj Party",
        "partyUrl": "https://www.indiavotes.com/party/ac_info/1381/220/60"
      },
      {
        "position": 6,
        "candidate": "Niyaj Ali Manju",
        "votes": 1263,
        "voteShare": 0.8,
        "party": "Rashtriya Lokmanch",
        "partyUrl": "https://www.indiavotes.com/party/ac_info/1307/220/60"
      },
      {
        "position": 7,
        "candidate": "Sabir",
        "votes": 1209,
        "voteShare": 0.8,
        "party": "Independent",
        "partyUrl": "https://www.indiavotes.com/party/ac_info/7/220/60"
      },
      {
        "position": 8,
        "candidate": "Comred Nijamuddin",
        "votes": 993,
        "voteShare": 0.7,
        "party": "Communist Party Of India",
        "partyUrl": "https://www.indiavotes.com/party/ac_info/14/220/60"
      },
      {
        "position": 9,
        "candidate": "Haji Margub Ahamad",
        "votes": 727,
        "voteShare": 0.5,
        "party": "Rashtriya Ulama Council",
        "partyUrl": "https://www.indiavotes.com/party/ac_info/1306/220/60"
      },
      {
        "position": 10,
        "candidate": "Vinod Kumar Seth",
        "votes": 549,
        "voteShare": 0.4,
        "party": "Independent",
        "partyUrl": "https://www.indiavotes.com/party/ac_info/7/220/60"
      },
      {
        "position": 11,
        "candidate": "Dinanath Dev Vanshi",
        "votes": 437,
        "voteShare": 0.3,
        "party": "Manavadhikar Janshakti Party",
        "partyUrl": "https://www.indiavotes.com/party/ac_info/1302/220/60"
      },
      {
        "position": 12,
        "candidate": "Kumar Saurabh",
        "votes": 371,
        "voteShare": 0.2,
        "party": "Pragtisheel Manav Samaj Party",
        "partyUrl": "https://www.indiavotes.com/party/ac_info/424/220/60"
      }
    ]
  }
}
