{
  "generatedAt": "2026-03-09T15:39:14.980Z",
  "source": "indiavotes",
  "parentSelection": {
    "state": "west-bengal",
    "stateLabel": "West Bengal",
    "stateVersionSlug": "west-bengal",
    "geographyVersionId": "west-bengal-default",
    "house": "VS",
    "year": 2016,
    "electionId": 249,
    "stateId": 9
  },
  "constituency": "Dhupguri",
  "constituencyNumber": 15,
  "district": "Jalpaiguri",
  "reservationType": "SC",
  "detailFileName": "west-bengal-vs-2016-15-dhupguri-detail.json",
  "note": "Local constituency detail captured from IndiaVotes and staged inside Election Atlas so the atlas no longer needs an outbound click for this seat.",
  "parsed": {
    "winner": {
      "position": 1,
      "candidate": "Mitali Roy",
      "votes": 90781,
      "voteShare": 44.2,
      "party": "All India Trinamool Congress",
      "partyUrl": "https://www.indiavotes.com/party/ac_info/575/249/9"
    },
    "runnerUp": {
      "position": 2,
      "candidate": "Mamata Roy",
      "votes": 71517,
      "voteShare": 34.8,
      "party": "Communist Party Of India (Marxist)",
      "partyUrl": "https://www.indiavotes.com/party/ac_info/1119/249/9"
    },
    "partyVoteTotals": [
      {
        "party": "All India Trinamool Congress",
        "votes": 90781
      },
      {
        "party": "Communist Party Of India (Marxist)",
        "votes": 71517
      },
      {
        "party": "Bharatiya Janta Party",
        "votes": 36167
      },
      {
        "party": "Socialist Unity Centre Of India (COMMUNIST)",
        "votes": 2361
      },
      {
        "party": "Bahujan Samaj Party",
        "votes": 2002
      }
    ],
    "candidateRows": [
      {
        "position": 1,
        "candidate": "Mitali Roy",
        "votes": 90781,
        "voteShare": 44.2,
        "party": "All India Trinamool Congress",
        "partyUrl": "https://www.indiavotes.com/party/ac_info/575/249/9"
      },
      {
        "position": 2,
        "candidate": "Mamata Roy",
        "votes": 71517,
        "voteShare": 34.8,
        "party": "Communist Party Of India (Marxist)",
        "partyUrl": "https://www.indiavotes.com/party/ac_info/1119/249/9"
      },
      {
        "position": 3,
        "candidate": "Agun Roy",
        "votes": 36167,
        "voteShare": 17.6,
        "party": "Bharatiya Janta Party",
        "partyUrl": "https://www.indiavotes.com/party/ac_info/143/249/9"
      },
      {
        "position": 5,
        "candidate": "Niranjan Roy",
        "votes": 2361,
        "voteShare": 1.2,
        "party": "Socialist Unity Centre Of India (COMMUNIST)",
        "partyUrl": "https://www.indiavotes.com/party/ac_info/1456/249/9"
      },
      {
        "position": 6,
        "candidate": "Beddyuti Roy",
        "votes": 2002,
        "voteShare": 1,
        "party": "Bahujan Samaj Party",
        "partyUrl": "https://www.indiavotes.com/party/ac_info/1381/249/9"
      }
    ]
  }
}
